{
    "backend": "django",
    "db_name": "",
    "db_pass": "",
    "db_type": "sqlite",
    "db_user": "",
    "dbms": "1",
    "description": "generated product",
    "design": "soft-ui-dashboard",
    "docker": "1",
    "err_code": 0,
    "frontend": "",
    "heroku": "0",
    "pattern": "mvc",
    "pro": "0",
    "task_id": "ce2de813-dd6a-4c2e-831e-1ed0ca072363",
    "task_info": "Upload Sources [0%] - 348 files",
    "task_output": "ce2de813-dd6a-4c2e-831e-1ed0ca072363.zip",
    "task_result": "SUCCESS",
    "task_state": "RUNNING",
    "task_ts_end": "2022-08-24-13-54-48",
    "task_ts_start": "2022-08-24-13-54-45"
}